tabular_ml_toolkit/__init__.py
tabular_ml_toolkit/_nbdev.py
tabular_ml_toolkit/dataframeloader.py
tabular_ml_toolkit/logger.py
tabular_ml_toolkit/preprocessor.py
tabular_ml_toolkit/tmlt.py
tabular_ml_toolkit/utility.py
tabular_ml_toolkit/xgb_optuna_objective.py
tabular_ml_toolkit-0.0.35.dist-info/LICENSE
tabular_ml_toolkit-0.0.35.dist-info/METADATA
tabular_ml_toolkit-0.0.35.dist-info/WHEEL
tabular_ml_toolkit-0.0.35.dist-info/entry_points.txt
tabular_ml_toolkit-0.0.35.dist-info/top_level.txt
tabular_ml_toolkit-0.0.35.dist-info/RECORD
