Metadata-Version: 2.1
Name: tabular-ml-toolkit
Version: 0.0.35
Summary: A helper library to jumpstart your machine learning project based on tabular or structured data.
Home-page: https://github.com/psmathur/tabular_ml_toolkit/tree/master/
Author: Pankaj Mathur
Author-email: psmathur.public@gmail.com
License: Apache Software License 2.0
Keywords: machine learning,tabular data,scikit-learn,XGBoost
Platform: UNKNOWN
Classifier: Development Status :: 3 - Alpha
Classifier: Intended Audience :: Developers
Classifier: Natural Language :: English
Classifier: Programming Language :: Python :: 3.6
Classifier: Programming Language :: Python :: 3.7
Classifier: Programming Language :: Python :: 3.8
Classifier: License :: OSI Approved :: Apache Software License
Requires-Python: >=3.6
License-File: LICENSE
Requires-Dist: pip
Requires-Dist: packaging
Requires-Dist: pandas (==1.1.5)
Requires-Dist: scikit-learn (==1.0.0)
Requires-Dist: xgboost (==1.5.0)
Requires-Dist: optuna (==2.10.0)
Requires-Dist: pytorch-tabnet (==3.1.1)
Provides-Extra: dev
